blog/__init__.py
blog/adminforms.py
blog/adminx.py
blog/apis.py
blog/apps.py
blog/models.py
blog/rss.py
blog/serializers.py
blog/sitemap.py
blog/tests.py
blog/views.py
blog/middleware/__init__.py
blog/middleware/user_id.py
blog/migrations/0001_initial.py
blog/migrations/0002_auto_20190704_1557.py
blog/migrations/0003_post_content_html.py
blog/migrations/0004_post_is_md.py
blog/migrations/__init__.py
comment/__init__.py
comment/adminx.py
comment/apps.py
comment/forms.py
comment/models.py
comment/tests.py
comment/views.py
comment/migrations/0001_initial.py
comment/migrations/0002_auto_20190709_0536.py
comment/migrations/__init__.py
comment/templatetags/__init__.py
comment/templatetags/comment_block.py
config/__init__.py
config/adminx.py
config/apps.py
config/models.py
config/tests.py
config/views.py
config/migrations/0001_initial.py
config/migrations/__init__.py
myidea/__init__.py
myidea/autocomplete.py
myidea/base_admin.py
myidea/custom_site.py
myidea/storage.py
myidea/urls.py
myidea/wsgi.py
myidea/settings/__init__.py
myidea/settings/base.py
myidea/settings/develop.py
myidea/settings/product.py
myidea-0.1.data/scripts/manage.py
myidea-0.1.dist-info/METADATA
myidea-0.1.dist-info/WHEEL
myidea-0.1.dist-info/entry_points.txt
myidea-0.1.dist-info/top_level.txt
myidea-0.1.dist-info/RECORD
